PyHaier/Get3way.py
PyHaier/GetArchError.py
PyHaier/GetCHTemp.py
PyHaier/GetCompInfo.py
PyHaier/GetDHWCurTemp.py
PyHaier/GetDHWTemp.py
PyHaier/GetEEVLevel.py
PyHaier/GetError.py
PyHaier/GetFanRpm.py
PyHaier/GetMode.py
PyHaier/GetPdPs.py
PyHaier/GetPump.py
PyHaier/GetState.py
PyHaier/GetTSatPd.py
PyHaier/GetTSatPs.py
PyHaier/GetTao.py
PyHaier/GetTdTs.py
PyHaier/GetTdef.py
PyHaier/GetThiTho.py
PyHaier/GetTwiTwo.py
PyHaier/SetCHTemp.py
PyHaier/SetDHWTemp.py
PyHaier/SetMode.py
PyHaier/SetState.py
PyHaier/__init__.py
pyhaier-0.3.6.dist-info/METADATA
pyhaier-0.3.6.dist-info/WHEEL
pyhaier-0.3.6.dist-info/top_level.txt
pyhaier-0.3.6.dist-info/RECORD
