Metadata-Version: 2.4
Name: PyHaier
Version: 0.3.6
Summary: Very simple library to manipulate the basic parameters of the Haier heat pump.
Author-email: Jacek Brzozowski <jacekbrzozowski.pld@gmail.com>
Project-URL: Homepage, https://github.com/ktostam/PyHaier
Project-URL: Bug Tracker, https://github.com/ktostam/PyHaier/issues
Classifier: Development Status :: 4 - Beta
Classifier: Programming Language :: Python :: 3
Classifier: License :: OSI Approved :: GNU Affero General Public License v3
Classifier: Operating System :: POSIX :: Linux
Requires-Python: >=3.7
